mojo/interfaces/__init__.py
mojo/interfaces/ibasiccredential.py
mojo/interfaces/iexcludefilter.py
mojo/interfaces/iincludefilter.py
mojo/interfaces/iserializable.py
mojo/interfaces/isystemcontext.py
mojo_interfaces-2.0.3.dist-info/LICENSE.txt
mojo_interfaces-2.0.3.dist-info/METADATA
mojo_interfaces-2.0.3.dist-info/WHEEL
mojo_interfaces-2.0.3.dist-info/RECORD
